LICENSE.txt
MANIFEST.in
README.md
setup.cfg
setup.py
AutoFun/AutoFun.pyd
AutoFun/__init__.py
AutoFun.egg-info/PKG-INFO
AutoFun.egg-info/SOURCES.txt
AutoFun.egg-info/dependency_links.txt
AutoFun.egg-info/top_level.txt
AutoFun/CutPdf/CutPdf.pyd
AutoFun/CutPdf/__init__.py
AutoFun/CutPdf/Function/__init__.py
AutoFun/CutPdf/Function/cut_pdF_pic.exe
AutoFun/CutPdf/Function/optionDb.pyd
AutoFun/CutPdf/Ui/CutPdfPicUi.pyd
AutoFun/CutPdf/Ui/__init__.py
AutoFun/OcrFinish/OcrFinish.pyd
AutoFun/OcrFinish/__init__.py
AutoFun/OcrFinish/Ui/OcrfinishUi.pyd
AutoFun/OcrFinish/Ui/__init__.py
AutoFun/OcrPicFun/OcrPicFun.pyd
AutoFun/OcrPicFun/__init__.py
AutoFun/OcrPicFun/Function/__init__.py
AutoFun/OcrPicFun/Function/dict_to_json.pyd
AutoFun/OcrPicFun/Function/get_json.pyd
AutoFun/OcrPicFun/Function/splitJpg.pyd
AutoFun/OcrPicFun/Ui/OcrparameterUi.pyd
AutoFun/OcrPicFun/Ui/__init__.py
AutoFun/OcrTableFun/OcrTableFun.pyd
AutoFun/OcrTableFun/__init__.py
AutoFun/OcrTableFun/Function/DB_in_sqlite.pyd
AutoFun/OcrTableFun/Function/__init__.py
AutoFun/OcrTableFun/Function/corpus.pickle
AutoFun/OcrTableFun/Function/dictionary.dict
AutoFun/OcrTableFun/Function/optionDb.pyd
AutoFun/OcrTableFun/Function/saveLoad.py
AutoFun/OcrTableFun/Function/sqlite_to_excel.pyd
AutoFun/OcrTableFun/Function/tfidf.model
AutoFun/OcrTableFun/Function/txt_OCR.db
AutoFun/OcrTableFun/Ui/OcrTableUi.pyd
AutoFun/OcrTableFun/Ui/__init__.py
AutoFun/QcloudApi/__init__.py
AutoFun/QcloudApi/qcloudapi.py
AutoFun/QcloudApi/common/__init__.py
AutoFun/QcloudApi/common/api_exception.py
AutoFun/QcloudApi/common/request.py
AutoFun/QcloudApi/common/sign.py
AutoFun/QcloudApi/modules/__init__.py
AutoFun/QcloudApi/modules/account.py
AutoFun/QcloudApi/modules/apigateway.py
AutoFun/QcloudApi/modules/athena.py
AutoFun/QcloudApi/modules/base.py
AutoFun/QcloudApi/modules/batch.py
AutoFun/QcloudApi/modules/bgpip.py
AutoFun/QcloudApi/modules/bill.py
AutoFun/QcloudApi/modules/bm.py
AutoFun/QcloudApi/modules/bmeip.py
AutoFun/QcloudApi/modules/bmlb.py
AutoFun/QcloudApi/modules/bmvpc.py
AutoFun/QcloudApi/modules/cbs.py
AutoFun/QcloudApi/modules/ccr.py
